mosaik_pandapower/__init__.py
mosaik_pandapower/model.py
mosaik_pandapower/simulator.py
mosaik_pandapower-0.2.2.dist-info/AUTHORS.txt
mosaik_pandapower-0.2.2.dist-info/LICENSE
mosaik_pandapower-0.2.2.dist-info/METADATA
mosaik_pandapower-0.2.2.dist-info/WHEEL
mosaik_pandapower-0.2.2.dist-info/entry_points.txt
mosaik_pandapower-0.2.2.dist-info/top_level.txt
mosaik_pandapower-0.2.2.dist-info/RECORD
