Metadata-Version: 2.1
Name: mosaik-pandapower
Version: 0.2.2
Summary: An adapter to use pandapower with mosaik.
Home-page: https://gitlab.com/mosaik/components/energy/mosaik-pandapower
Author: Rami Elshinawy
Author-email: mosaik@offis.de
License: UNKNOWN
Platform: UNKNOWN
Classifier: Development Status :: 4 - Beta
Classifier: Environment :: Console
Classifier: Intended Audience :: Science/Research
Classifier: License :: OSI Approved :: GNU Lesser General Public License v2 (LGPLv2)
Classifier: Natural Language :: English
Classifier: Operating System :: OS Independent
Classifier: Programming Language :: Python
Classifier: Programming Language :: Python :: 3
Classifier: Programming Language :: Python :: 3.6
Classifier: Programming Language :: Python :: 3.7
Classifier: Programming Language :: Python :: 3.8
Classifier: Topic :: Scientific/Engineering
License-File: LICENSE
License-File: AUTHORS.txt
